RPA/recognition/__init__.py
RPA/recognition/ocr.py
RPA/recognition/templates.py
RPA/recognition/utils.py
rpaframework_recognition-5.2.7.dist-info/LICENSE
rpaframework_recognition-5.2.7.dist-info/METADATA
rpaframework_recognition-5.2.7.dist-info/WHEEL
rpaframework_recognition-5.2.7.dist-info/RECORD
